setup.py
django_simple_invoice.egg-info/PKG-INFO
django_simple_invoice.egg-info/SOURCES.txt
django_simple_invoice.egg-info/dependency_links.txt
django_simple_invoice.egg-info/not-zip-safe
django_simple_invoice.egg-info/requires.txt
django_simple_invoice.egg-info/top_level.txt
invoice/__init__.py
invoice/admin.py
invoice/admin_actions.py
invoice/context_processors.py
invoice/export.py
invoice/export_example.py
invoice/forms.py
invoice/models.py
invoice/pdf.py
invoice/pdf_example.py
invoice/test_settings.py
invoice/test_urls.py
invoice/tests.py
invoice/views.py
invoice/conf/__init__.py
invoice/conf/settings.py
invoice/management/__init__.py
invoice/management/commands/__init__.py
invoice/management/commands/send_invoices.py
invoice/migrations/0001_initial.py
invoice/migrations/__init__.py
invoice/utils/__init__.py
invoice/utils/friendly_id.py
invoice/utils/naming.py