Metadata-Version: 1.1
Name: django-simple-invoice
Version: 0.3.4
Summary: Invoicing application for Django
Home-page: https://github.com/mwolff44/django-simple-invoice
Author: Thomas Loiret, Mathias Wolff
Author-email: mathiaswolff@mac.com
License: GPL v3
Keywords: invoice django application pdf
Platform: UNKNOWN
Classifier: Development Status :: 3 - Alpha
Classifier: Environment :: Web Environment
Classifier: Intended Audience :: Developers
Classifier: Operating System :: OS Independent
Classifier: Programming Language :: Python
Classifier: Framework :: Django
